nnkrxx/__init__.py
nnkrxx/main.py
nnkrxx-0.2.dist-info/METADATA
nnkrxx-0.2.dist-info/WHEEL
nnkrxx-0.2.dist-info/entry_points.txt
nnkrxx-0.2.dist-info/top_level.txt
nnkrxx-0.2.dist-info/RECORD
