Metadata-Version: 2.1
Name: nnkrxx
Version: 0.2
Author: R. NAVEEN NITHYA KALYAN
Author-email: naveennithyakalyan@gmail.com
Classifier: License :: OSI Approved :: MIT License
